pynormalize/__init__.py
pynormalize/pynormalize.py
pynormalize/version.py
pynormalize-0.1.4.dist-info/DESCRIPTION.rst
pynormalize-0.1.4.dist-info/METADATA
pynormalize-0.1.4.dist-info/RECORD
pynormalize-0.1.4.dist-info/WHEEL
pynormalize-0.1.4.dist-info/entry_points.txt
pynormalize-0.1.4.dist-info/metadata.json
pynormalize-0.1.4.dist-info/top_level.txt
