Metadata-Version: 2.0
Name: pynormalize
Version: 0.1.4
Summary: Audio normalization for Python
Home-page: https://github.com/giannisterzopoulos/pynormalize
Author: Giannis Terzopoulos
Author-email: terzo.giannis@gmail.com
License: MIT
Platform: UNKNOWN
Classifier: Development Status :: 4 - Beta
Classifier: Intended Audience :: Developers
Classifier: License :: OSI Approved :: MIT License
Classifier: Natural Language :: English
Classifier: Programming Language :: Python :: 3
Classifier: Programming Language :: Python :: 3.4
Classifier: Programming Language :: Python :: 3.5
Classifier: Programming Language :: Python :: 3.6
Requires-Dist: pydub (>=0.21.0)
Requires-Dist: mutagen (>=1.40.0)
